setup.py
bss_client/__init__.py
bss_client/client.py
bss_client/exception.py
bss_client/request.py
bss_client.egg-info/PKG-INFO
bss_client.egg-info/SOURCES.txt
bss_client.egg-info/dependency_links.txt
bss_client.egg-info/requires.txt
bss_client.egg-info/top_level.txt
tests/__init__.py
tests/test_client.py
tests/test_request.py