Metadata-Version: 1.0
Name: bss-client
Version: 0.2.0
Summary: CPBM BSS API client.
Home-page: https://github.com/globocom/python-bss-client
Author: tsuru
Author-email: tsuru@corp.globo.com
License: UNKNOWN
Platform: UNKNOWN
